openbadges/__init__.py
openbadges/command_line.py
openbadges/version.py
openbadges/verifier/__init__.py
openbadges/verifier/exceptions.py
openbadges/verifier/logger.py
openbadges/verifier/openbadges_context.py
openbadges/verifier/state.py
openbadges/verifier/utils.py
openbadges/verifier/verifier.py
openbadges/verifier/actions/__init__.py
openbadges/verifier/actions/action_types.py
openbadges/verifier/actions/graph.py
openbadges/verifier/actions/input.py
openbadges/verifier/actions/tasks.py
openbadges/verifier/actions/utils.py
openbadges/verifier/actions/validation_report.py
openbadges/verifier/extensions/__init__.py
openbadges/verifier/reducers/__init__.py
openbadges/verifier/reducers/graph.py
openbadges/verifier/reducers/input.py
openbadges/verifier/reducers/tasks.py
openbadges/verifier/reducers/verification_report.py
openbadges/verifier/server/__init__.py
openbadges/verifier/server/app.py
openbadges/verifier/server/static/screen.css
openbadges/verifier/server/templates/base.html
openbadges/verifier/server/templates/index.html
openbadges/verifier/server/templates/results.html
openbadges/verifier/tasks/__init__.py
openbadges/verifier/tasks/crypto.py
openbadges/verifier/tasks/extensions.py
openbadges/verifier/tasks/graph.py
openbadges/verifier/tasks/images.py
openbadges/verifier/tasks/input.py
openbadges/verifier/tasks/object_upgrades.py
openbadges/verifier/tasks/task_types.py
openbadges/verifier/tasks/utils.py
openbadges/verifier/tasks/validation.py
openbadges/verifier/tasks/verification.py
badgecheck-1.2.0.dist-info/LICENSE
badgecheck-1.2.0.dist-info/METADATA
badgecheck-1.2.0.dist-info/WHEEL
badgecheck-1.2.0.dist-info/entry_points.txt
badgecheck-1.2.0.dist-info/top_level.txt
badgecheck-1.2.0.dist-info/RECORD
